{
  "template_version": 1,
  "source": {
    "base_op": 48407,
    "tipo_docto": "OPS",
    "database": "UNOEE"
  },
  "header": {
    "f850_id_cia": 1,
    "f850_id_co": "001",
    "f850_id_tipo_docto": "OPS",
    "f850_id_fecha": "2025-03-18T00:00:00",
    "f850_id_grupo_clase_docto": 701,
    "f850_id_clase_docto": 701,
    "f850_id_clase_op": "OPD",
    "f850_ind_tipo_op": 0,
    "f850_ind_multiples_items": 0,
    "f850_ind_consolida_comp_oper": 0,
    "f850_ind_requiere_lm": 1,
    "f850_ind_genera_ordenes_comp": 1,
    "f850_ind_genera_misma_orden": 1,
    "f850_ind_genera_todos_niveles": 1,
    "f850_ind_genera_solo_faltantes": 0,
    "f850_ind_metodo_lista_op": 1,
    "f850_ind_controla_tep": 1,
    "f850_ind_genera_consumos_tep": 0,
    "f850_ind_genera_entradas_tep": 0,
    "f850_id_clase_op_generar": null,
    "f850_ind_confirmar_al_aprobar": 1,
    "f850_ind_distribucion_costos": 0,
    "f850_ind_devolucion_comp": 1,
    "f850_ind_estado": 3,
    "f850_fecha_cumplida": "2025-09-30T00:00:00",
    "f850_rowid_tercero_planif": 12,
    "f850_id_instalacion": "001",
    "f850_rowid_op_padre": null,
    "f850_ind_transmitido": 0,
    "f850_ind_impresion": 1,
    "f850_nro_impresiones": 1,
    "f850_ind_posdeduccion": 0,
    "f850_ind_pedido_venta": 0,
    "f850_rowid_pv_docto": null,
    "f850_ind_posdeduccion_tep": 0,
    "f850_ind_reg_incons_posd": 0,
    "f850_ind_lote_automatico": 0,
    "f850_ind_controlar_cant_ext": 1,
    "f850_ind_incluir_operacion": 1,
    "f850_ind_entrega_estandar": 0,
    "f850_ind_valida_consumo_tot": 0,
    "f850_ind_liq_tep_estandar": 0,
    "f850_ind_no_liq_tep": 0
  },
  "refs": {
    "referencia_1": "",
    "referencia_2": "",
    "referencia_3": "",
    "notas": ""
  }
}